taskick/__init__.py
taskick/__main__.py
taskick/details.py
taskick/runner.py
taskick/utils.py
taskick-0.1.6.dist-info/LICENSE
taskick-0.1.6.dist-info/WHEEL
taskick-0.1.6.dist-info/METADATA
taskick-0.1.6.dist-info/RECORD
