Metadata-Version: 2.1
Name: taskick
Version: 0.1.6
Summary: Taskick is an event-driven Python library that automatically executes scripts or any commands.
Home-page: https://github.com/atsuyaide/taskick
Author: Atsuya Ide
Author-email: atsuya.ide528@gmail.com
Requires-Python: >=3.8,<4.0
Classifier: Programming Language :: Python :: 3
Classifier: Programming Language :: Python :: 3.10
Classifier: Programming Language :: Python :: 3.8
Classifier: Programming Language :: Python :: 3.9
Requires-Dist: PyYAML (>=6.0,<7.0)
Requires-Dist: schedule (>=1.1.0,<2.0.0)
Requires-Dist: watchdog (>=2.1.6,<3.0.0)
Project-URL: Repository, https://github.com/atsuyaide/taskick
